autodocify_cli/__init__.py
autodocify_cli/cli.py
autodocify_cli/core/exceptions.py
autodocify_cli/core/settings/__init__.py
autodocify_cli/core/settings/config.py
autodocify_cli/lib/__init__.py
autodocify_cli/lib/generators/doc_generator.py
autodocify_cli/lib/generators/helper.py
autodocify_cli/lib/generators/readme_generator.py
autodocify_cli/lib/generators/swagger_docs_generator.py
autodocify_cli/lib/generators/test_generator.py
autodocify_cli/lib/get_general_project_files.py
autodocify_cli/lib/loaders/yaspin.py
autodocify_cli/lib/project_content_merger.py
autodocify_cli/lib/prompt_templates/readme_prompt_template.py
autodocify_cli/lib/prompt_templates/swagger_prompt_template.py
autodocify_cli/lib/prompt_templates/technical_doc_prompt_template.py
autodocify_cli/lib/prompt_templates/test_prompt_template.py
autodocify_cli/lib/services/Bard.py
autodocify_cli/lib/services/Gemini.py
autodocify_cli/lib/services/OpenAI.py
autodocify_cli/lib/services/__init__.py
autodocify_cli/lib/services/ai_integration.py
autodocify_cli/lib/utils.py
autodocify_cli-0.4.5.dist-info/METADATA
autodocify_cli-0.4.5.dist-info/WHEEL
autodocify_cli-0.4.5.dist-info/entry_points.txt
autodocify_cli-0.4.5.dist-info/RECORD
