Metadata-Version: 2.3
Name: autodocify-cli
Version: 0.4.5
Summary: AutoDocify is a command-line interface (CLI) tool designed to automate the generation of project documentation and placeholder test files. Leveraging the power of Large Language Models (LLMs), AutoDocify streamlines your development workflow by creating professional READMEs, basic technical documentation, and a starting point for your testing strategy
License: Proprietary
Keywords: autodoc,documentation,automation,readme,tests,python,cli,llm,ai,developer,productivity,pytest,unittest,devtools
Author: AlexAdedeji
Author-email: alexadedeji15@gmail.com
Requires-Python: >=3.12,<4.0
Classifier: Intended Audience :: Developers
Classifier: Development Status :: 3 - Alpha
Classifier: Programming Language :: Python :: 3.12
Classifier: Environment :: Console
Classifier: Operating System :: OS Independent
Classifier: Topic :: Documentation
Classifier: Topic :: Software Development :: Build Tools
Classifier: Topic :: Software Development :: Code Generators
Classifier: Topic :: Software Development :: Documentation
Requires-Dist: halo (>=0.0.31,<0.0.32)
Requires-Dist: pydantic-settings (>=2.7.1,<3.0.0)
Requires-Dist: rich (>=13.9.4,<14.0.0)
Requires-Dist: typer (>=0.15.1,<0.16.0)
Requires-Dist: yaspin (>=3.1.0,<4.0.0)
Project-URL: Homepage, https://github.com/grayStone-Inc/autodocify-cli
Project-URL: Issues, https://github.com/grayStone-Inc/autodocify-cli/issues
Project-URL: Repository, https://github.com/grayStone-Inc/autodocify-cli
